clutchless/__init__.py
clutchless/command/__init__.py
clutchless/command/add.py
clutchless/command/archive.py
clutchless/command/command.py
clutchless/command/dedupe.py
clutchless/command/find.py
clutchless/command/link.py
clutchless/command/organize.py
clutchless/command/other.py
clutchless/command/prune/__init__.py
clutchless/command/prune/client.py
clutchless/command/prune/folder.py
clutchless/command/prune/main.py
clutchless/command/rename.py
clutchless/configuration.py
clutchless/domain/__init__.py
clutchless/domain/torrent.py
clutchless/entrypoints/__init__.py
clutchless/entrypoints/cli.py
clutchless/external/__init__.py
clutchless/external/filesystem.py
clutchless/external/metainfo.py
clutchless/external/result.py
clutchless/external/transmission.py
clutchless/service/__init__.py
clutchless/service/file.py
clutchless/service/torrent.py
clutchless/spec/__init__.py
clutchless/spec/add.py
clutchless/spec/archive.py
clutchless/spec/dedupe.py
clutchless/spec/find.py
clutchless/spec/link.py
clutchless/spec/organize.py
clutchless/spec/prune/__init__.py
clutchless/spec/prune/client.py
clutchless/spec/prune/folder.py
clutchless/spec/prune/main.py
clutchless/spec/rename.py
clutchless/spec/shared.py
clutchless/stream.py
clutchless-0.2.1.dist-info/entry_points.txt
clutchless-0.2.1.dist-info/LICENSE
clutchless-0.2.1.dist-info/WHEEL
clutchless-0.2.1.dist-info/METADATA
clutchless-0.2.1.dist-info/RECORD
