Metadata-Version: 2.1
Name: clutchless
Version: 0.2.1
Summary: A CLI tool to manage torrents and their data in Transmission
Home-page: https://github.com/mhadam/clutchless
License: MIT
Author: mhadam
Author-email: michael@hadam.us
Requires-Python: >=3.7,<4.0
Classifier: License :: OSI Approved :: MIT License
Classifier: Programming Language :: Python :: 3
Classifier: Programming Language :: Python :: 3.7
Classifier: Programming Language :: Python :: 3.8
Classifier: Programming Language :: Python :: 3.9
Requires-Dist: colorama (>=0.4.4,<0.5.0)
Requires-Dist: docopt (>=0.6.2,<0.7.0)
Requires-Dist: pathvalidate (>=2.4.1,<3.0.0)
Requires-Dist: texttable (>=1.6.3,<2.0.0)
Requires-Dist: torrentool (>=1.1.0,<2.0.0)
Requires-Dist: transmission-clutch (>=6.0.0,<7.0.0)
Project-URL: Documentation, https://github.com/mhadam/clutchless
Project-URL: Repository, https://github.com/mhadam/clutchless
